{
  "stockId": "5347",
  "startDate": "2026-06-09",
  "endDate": "2026-06-29",
  "prices": [
    {
      "date": "2026-06-09",
      "open": 158.5,
      "high": 163,
      "low": 153.5,
      "close": 161,
      "volume": 24191407
    },
    {
      "date": "2026-06-10",
      "open": 158,
      "high": 161.5,
      "low": 151.5,
      "close": 152.5,
      "volume": 24971516
    },
    {
      "date": "2026-06-11",
      "open": 153,
      "high": 161.5,
      "low": 151.5,
      "close": 161.5,
      "volume": 35275851
    },
    {
      "date": "2026-06-12",
      "open": 169,
      "high": 173.5,
      "low": 168,
      "close": 169.5,
      "volume": 34610126
    },
    {
      "date": "2026-06-15",
      "open": 174.5,
      "high": 176.5,
      "low": 170.5,
      "close": 174.5,
      "volume": 27630938
    },
    {
      "date": "2026-06-16",
      "open": 177,
      "high": 177,
      "low": 169,
      "close": 171.5,
      "volume": 20599903
    },
    {
      "date": "2026-06-17",
      "open": 169.5,
      "high": 169.5,
      "low": 164.5,
      "close": 166.5,
      "volume": 12490377
    },
    {
      "date": "2026-06-18",
      "open": 167,
      "high": 174.5,
      "low": 165,
      "close": 174.5,
      "volume": 17239914
    },
    {
      "date": "2026-06-22",
      "open": 191.5,
      "high": 191.5,
      "low": 191.5,
      "close": 191.5,
      "volume": 16148766
    },
    {
      "date": "2026-06-23",
      "open": 201.5,
      "high": 201.5,
      "low": 183.5,
      "close": 186.5,
      "volume": 64397485
    },
    {
      "date": "2026-06-24",
      "open": 190,
      "high": 200,
      "low": 183.5,
      "close": 200,
      "volume": 67793895
    },
    {
      "date": "2026-06-25",
      "open": 202,
      "high": 220,
      "low": 195,
      "close": 220,
      "volume": 73847294
    },
    {
      "date": "2026-06-26",
      "open": 215,
      "high": 215.5,
      "low": 200,
      "close": 202,
      "volume": 61373969
    },
    {
      "date": "2026-06-29",
      "open": 206.5,
      "high": 215.5,
      "low": 203.5,
      "close": 208.5,
      "volume": 37579423
    }
  ],
  "chips": [
    {
      "date": "2026-06-09",
      "foreign_buy": 9285,
      "foreign_buy_avg": 160.28,
      "foreign_sell": 4728,
      "foreign_sell_avg": 159.11,
      "foreign_net": 4557,
      "top_foreign": [
        {
          "name": "星洲瑞銀",
          "buy": 3509,
          "buy_avg": 160.46,
          "sell": 911,
          "sell_avg": 157.82,
          "net": 2598
        },
        {
          "name": "摩根士丹利",
          "buy": 2364,
          "buy_avg": 159.94,
          "sell": 630,
          "sell_avg": 159.1,
          "net": 1734
        },
        {
          "name": "摩根大通",
          "buy": 925,
          "buy_avg": 160.62,
          "sell": 422,
          "sell_avg": 159.09,
          "net": 503
        },
        {
          "name": "上海匯豐",
          "buy": 247,
          "buy_avg": 160.78,
          "sell": 0,
          "sell_avg": 0,
          "net": 247
        },
        {
          "name": "花旗環球",
          "buy": 326,
          "buy_avg": 160.66,
          "sell": 81,
          "sell_avg": 160.95,
          "net": 245
        },
        {
          "name": "港商野村",
          "buy": 138,
          "buy_avg": 160.79,
          "sell": 0,
          "sell_avg": 0,
          "net": 138
        },
        {
          "name": "美林證券",
          "buy": 422,
          "buy_avg": 159.43,
          "sell": 347,
          "sell_avg": 158.62,
          "net": 75
        }
      ],
      "top_foreign_sellers": [
        {
          "name": "美商高盛亞",
          "buy": 1353,
          "buy_avg": 160.24,
          "sell": 2336,
          "sell_avg": 159.64,
          "net": -983
        }
      ]
    },
    {
      "date": "2026-06-10",
      "foreign_buy": 8564,
      "foreign_buy_avg": 154.76,
      "foreign_sell": 3538,
      "foreign_sell_avg": 156.54,
      "foreign_net": 5026,
      "top_foreign": [
        {
          "name": "摩根士丹利",
          "buy": 2788,
          "buy_avg": 154.71,
          "sell": 682,
          "sell_avg": 154.63,
          "net": 2106
        },
        {
          "name": "星洲瑞銀",
          "buy": 2111,
          "buy_avg": 153.5,
          "sell": 449,
          "sell_avg": 156.69,
          "net": 1662
        },
        {
          "name": "摩根大通",
          "buy": 1191,
          "buy_avg": 155.07,
          "sell": 689,
          "sell_avg": 157.17,
          "net": 502
        },
        {
          "name": "美商高盛亞",
          "buy": 1601,
          "buy_avg": 155.05,
          "sell": 1119,
          "sell_avg": 156.74,
          "net": 482
        },
        {
          "name": "花旗環球",
          "buy": 199,
          "buy_avg": 155.88,
          "sell": 33,
          "sell_avg": 156.91,
          "net": 166
        },
        {
          "name": "港商野村",
          "buy": 139,
          "buy_avg": 157.19,
          "sell": 28,
          "sell_avg": 159.11,
          "net": 111
        },
        {
          "name": "港商麥格理",
          "buy": 16,
          "buy_avg": 152.5,
          "sell": 0,
          "sell_avg": 0,
          "net": 16
        }
      ],
      "top_foreign_sellers": [
        {
          "name": "上海匯豐",
          "buy": 0,
          "buy_avg": 0,
          "sell": 10,
          "sell_avg": 154.13,
          "net": -10
        },
        {
          "name": "美林證券",
          "buy": 516,
          "buy_avg": 157.55,
          "sell": 523,
          "sell_avg": 157.56,
          "net": -7
        },
        {
          "name": "群益高盛",
          "buy": 3,
          "buy_avg": 157.17,
          "sell": 5,
          "sell_avg": 152.5,
          "net": -2
        }
      ]
    },
    {
      "date": "2026-06-11",
      "foreign_buy": 17493,
      "foreign_buy_avg": 159.41,
      "foreign_sell": 7097,
      "foreign_sell_avg": 159.01,
      "foreign_net": 10396,
      "top_foreign": [
        {
          "name": "美商高盛亞",
          "buy": 5361,
          "buy_avg": 159.28,
          "sell": 2292,
          "sell_avg": 158.4,
          "net": 3069
        },
        {
          "name": "摩根士丹利",
          "buy": 4695,
          "buy_avg": 159.92,
          "sell": 1988,
          "sell_avg": 159.09,
          "net": 2707
        },
        {
          "name": "星洲瑞銀",
          "buy": 2250,
          "buy_avg": 159.85,
          "sell": 419,
          "sell_avg": 158.77,
          "net": 1831
        },
        {
          "name": "美林證券",
          "buy": 2216,
          "buy_avg": 158.65,
          "sell": 656,
          "sell_avg": 158.8,
          "net": 1560
        },
        {
          "name": "港商麥格理",
          "buy": 730,
          "buy_avg": 159.69,
          "sell": 8,
          "sell_avg": 160.69,
          "net": 722
        },
        {
          "name": "摩根大通",
          "buy": 1165,
          "buy_avg": 158.69,
          "sell": 491,
          "sell_avg": 160.29,
          "net": 674
        },
        {
          "name": "港商野村",
          "buy": 722,
          "buy_avg": 159.46,
          "sell": 485,
          "sell_avg": 159.16,
          "net": 237
        },
        {
          "name": "上海匯豐",
          "buy": 30,
          "buy_avg": 160.2,
          "sell": 0,
          "sell_avg": 0,
          "net": 30
        }
      ],
      "top_foreign_sellers": [
        {
          "name": "花旗環球",
          "buy": 323,
          "buy_avg": 157.98,
          "sell": 744,
          "sell_avg": 160.07,
          "net": -421
        },
        {
          "name": "群益高盛",
          "buy": 1,
          "buy_avg": 158.44,
          "sell": 14,
          "sell_avg": 159.67,
          "net": -13
        }
      ]
    },
    {
      "date": "2026-06-12",
      "foreign_buy": 10886,
      "foreign_buy_avg": 170.44,
      "foreign_sell": 8434,
      "foreign_sell_avg": 170.16,
      "foreign_net": 2452,
      "top_foreign": [
        {
          "name": "花旗環球",
          "buy": 3359,
          "buy_avg": 170.42,
          "sell": 75,
          "sell_avg": 169.84,
          "net": 3284
        },
        {
          "name": "星洲瑞銀",
          "buy": 2126,
          "buy_avg": 170.83,
          "sell": 1138,
          "sell_avg": 169.84,
          "net": 988
        },
        {
          "name": "摩根士丹利",
          "buy": 1559,
          "buy_avg": 170.11,
          "sell": 618,
          "sell_avg": 169.83,
          "net": 941
        },
        {
          "name": "港商野村",
          "buy": 742,
          "buy_avg": 170.97,
          "sell": 69,
          "sell_avg": 169.51,
          "net": 673
        },
        {
          "name": "美林證券",
          "buy": 702,
          "buy_avg": 170.08,
          "sell": 121,
          "sell_avg": 170.13,
          "net": 581
        }
      ],
      "top_foreign_sellers": [
        {
          "name": "美商高盛亞",
          "buy": 2092,
          "buy_avg": 170.29,
          "sell": 4451,
          "sell_avg": 170.08,
          "net": -2359
        },
        {
          "name": "港商麥格理",
          "buy": 4,
          "buy_avg": 169.5,
          "sell": 844,
          "sell_avg": 171.13,
          "net": -840
        },
        {
          "name": "摩根大通",
          "buy": 294,
          "buy_avg": 170.27,
          "sell": 1102,
          "sell_avg": 170.29,
          "net": -808
        },
        {
          "name": "群益高盛",
          "buy": 8,
          "buy_avg": 171.74,
          "sell": 16,
          "sell_avg": 171.87,
          "net": -8
        }
      ]
    },
    {
      "date": "2026-06-15",
      "foreign_buy": 10101,
      "foreign_buy_avg": 174.05,
      "foreign_sell": 2859,
      "foreign_sell_avg": 173.65,
      "foreign_net": 7242,
      "top_foreign": [
        {
          "name": "美商高盛亞",
          "buy": 3563,
          "buy_avg": 174.29,
          "sell": 1089,
          "sell_avg": 174.08,
          "net": 2474
        },
        {
          "name": "摩根士丹利",
          "buy": 2261,
          "buy_avg": 173.67,
          "sell": 232,
          "sell_avg": 172.87,
          "net": 2029
        },
        {
          "name": "美林證券",
          "buy": 1154,
          "buy_avg": 174.2,
          "sell": 38,
          "sell_avg": 172.21,
          "net": 1116
        },
        {
          "name": "星洲瑞銀",
          "buy": 1387,
          "buy_avg": 174.31,
          "sell": 285,
          "sell_avg": 173.34,
          "net": 1102
        },
        {
          "name": "花旗環球",
          "buy": 581,
          "buy_avg": 172.84,
          "sell": 60,
          "sell_avg": 174.33,
          "net": 521
        },
        {
          "name": "港商野村",
          "buy": 106,
          "buy_avg": 174.4,
          "sell": 55,
          "sell_avg": 174.27,
          "net": 51
        },
        {
          "name": "港商麥格理",
          "buy": 16,
          "buy_avg": 174.66,
          "sell": 0,
          "sell_avg": 0,
          "net": 16
        }
      ],
      "top_foreign_sellers": [
        {
          "name": "摩根大通",
          "buy": 1030,
          "buy_avg": 174.15,
          "sell": 1081,
          "sell_avg": 173.44,
          "net": -51
        },
        {
          "name": "群益高盛",
          "buy": 2,
          "buy_avg": 173.21,
          "sell": 19,
          "sell_avg": 174.38,
          "net": -17
        }
      ]
    },
    {
      "date": "2026-06-16",
      "foreign_buy": 4222,
      "foreign_buy_avg": 172.5,
      "foreign_sell": 4731,
      "foreign_sell_avg": 172.18,
      "foreign_net": -510,
      "top_foreign": [
        {
          "name": "摩根士丹利",
          "buy": 1316,
          "buy_avg": 173.13,
          "sell": 951,
          "sell_avg": 171.76,
          "net": 365
        },
        {
          "name": "星洲瑞銀",
          "buy": 988,
          "buy_avg": 172.85,
          "sell": 772,
          "sell_avg": 172.48,
          "net": 216
        },
        {
          "name": "花旗環球",
          "buy": 131,
          "buy_avg": 173.93,
          "sell": 90,
          "sell_avg": 171.97,
          "net": 41
        }
      ],
      "top_foreign_sellers": [
        {
          "name": "摩根大通",
          "buy": 521,
          "buy_avg": 172.47,
          "sell": 952,
          "sell_avg": 172.08,
          "net": -431
        },
        {
          "name": "美林證券",
          "buy": 489,
          "buy_avg": 171.8,
          "sell": 831,
          "sell_avg": 172.32,
          "net": -342
        },
        {
          "name": "美商高盛亞",
          "buy": 716,
          "buy_avg": 171.02,
          "sell": 986,
          "sell_avg": 172.39,
          "net": -270
        },
        {
          "name": "港商野村",
          "buy": 59,
          "buy_avg": 173.5,
          "sell": 143,
          "sell_avg": 171.78,
          "net": -84
        },
        {
          "name": "上海匯豐",
          "buy": 0,
          "buy_avg": 0,
          "sell": 2,
          "sell_avg": 171.44,
          "net": -2
        },
        {
          "name": "群益高盛",
          "buy": 2,
          "buy_avg": 171.45,
          "sell": 4,
          "sell_avg": 172.26,
          "net": -2
        }
      ]
    },
    {
      "date": "2026-06-17",
      "foreign_buy": 1649,
      "foreign_buy_avg": 166.57,
      "foreign_sell": 6121,
      "foreign_sell_avg": 166.59,
      "foreign_net": -4472,
      "top_foreign": [
        {
          "name": "上海匯豐",
          "buy": 50,
          "buy_avg": 166.18,
          "sell": 0,
          "sell_avg": 0,
          "net": 50
        },
        {
          "name": "群益高盛",
          "buy": 3,
          "buy_avg": 166.71,
          "sell": 0,
          "sell_avg": 168.5,
          "net": 3
        }
      ],
      "top_foreign_sellers": [
        {
          "name": "摩根大通",
          "buy": 60,
          "buy_avg": 167.01,
          "sell": 2122,
          "sell_avg": 166.46,
          "net": -2062
        },
        {
          "name": "摩根士丹利",
          "buy": 308,
          "buy_avg": 167.1,
          "sell": 1297,
          "sell_avg": 166.21,
          "net": -989
        },
        {
          "name": "美商高盛亞",
          "buy": 450,
          "buy_avg": 166.29,
          "sell": 1051,
          "sell_avg": 166.75,
          "net": -601
        },
        {
          "name": "港商野村",
          "buy": 0,
          "buy_avg": 167,
          "sell": 550,
          "sell_avg": 167.09,
          "net": -550
        },
        {
          "name": "星洲瑞銀",
          "buy": 336,
          "buy_avg": 166.85,
          "sell": 596,
          "sell_avg": 166.46,
          "net": -260
        },
        {
          "name": "花旗環球",
          "buy": 10,
          "buy_avg": 165.85,
          "sell": 56,
          "sell_avg": 166.98,
          "net": -46
        },
        {
          "name": "美林證券",
          "buy": 431,
          "buy_avg": 166.27,
          "sell": 449,
          "sell_avg": 167.36,
          "net": -18
        }
      ]
    },
    {
      "date": "2026-06-18",
      "foreign_buy": 5829,
      "foreign_buy_avg": 171.82,
      "foreign_sell": 3976,
      "foreign_sell_avg": 170.63,
      "foreign_net": 1853,
      "top_foreign": [
        {
          "name": "摩根士丹利",
          "buy": 3306,
          "buy_avg": 171.96,
          "sell": 663,
          "sell_avg": 171.77,
          "net": 2643
        },
        {
          "name": "摩根大通",
          "buy": 888,
          "buy_avg": 171.99,
          "sell": 644,
          "sell_avg": 170.24,
          "net": 244
        },
        {
          "name": "港商麥格理",
          "buy": 147,
          "buy_avg": 174.5,
          "sell": 9,
          "sell_avg": 174.5,
          "net": 138
        },
        {
          "name": "港商野村",
          "buy": 127,
          "buy_avg": 168.48,
          "sell": 43,
          "sell_avg": 173.5,
          "net": 84
        },
        {
          "name": "花旗環球",
          "buy": 116,
          "buy_avg": 173.47,
          "sell": 62,
          "sell_avg": 173.09,
          "net": 54
        }
      ],
      "top_foreign_sellers": [
        {
          "name": "美商高盛亞",
          "buy": 798,
          "buy_avg": 171.47,
          "sell": 1571,
          "sell_avg": 171.4,
          "net": -773
        },
        {
          "name": "星洲瑞銀",
          "buy": 361,
          "buy_avg": 171.34,
          "sell": 864,
          "sell_avg": 168.54,
          "net": -503
        },
        {
          "name": "美林證券",
          "buy": 85,
          "buy_avg": 168.01,
          "sell": 114,
          "sell_avg": 168.73,
          "net": -29
        },
        {
          "name": "上海匯豐",
          "buy": 0,
          "buy_avg": 0,
          "sell": 3,
          "sell_avg": 174.19,
          "net": -3
        },
        {
          "name": "群益高盛",
          "buy": 0,
          "buy_avg": 169.78,
          "sell": 2,
          "sell_avg": 173.14,
          "net": -2
        }
      ]
    },
    {
      "date": "2026-06-22",
      "foreign_buy": 241,
      "foreign_buy_avg": 191.5,
      "foreign_sell": 3219,
      "foreign_sell_avg": 191.5,
      "foreign_net": -2978,
      "top_foreign": [
        {
          "name": "美林證券",
          "buy": 215,
          "buy_avg": 191.5,
          "sell": 53,
          "sell_avg": 191.5,
          "net": 162
        }
      ],
      "top_foreign_sellers": [
        {
          "name": "摩根士丹利",
          "buy": 1,
          "buy_avg": 191.5,
          "sell": 1154,
          "sell_avg": 191.5,
          "net": -1153
        },
        {
          "name": "花旗環球",
          "buy": 1,
          "buy_avg": 191.5,
          "sell": 907,
          "sell_avg": 191.5,
          "net": -906
        },
        {
          "name": "摩根大通",
          "buy": 0,
          "buy_avg": 0,
          "sell": 399,
          "sell_avg": 191.5,
          "net": -399
        },
        {
          "name": "星洲瑞銀",
          "buy": 22,
          "buy_avg": 191.5,
          "sell": 369,
          "sell_avg": 191.5,
          "net": -347
        },
        {
          "name": "美商高盛亞",
          "buy": 0,
          "buy_avg": 0,
          "sell": 323,
          "sell_avg": 191.5,
          "net": -323
        },
        {
          "name": "群益高盛",
          "buy": 2,
          "buy_avg": 191.5,
          "sell": 14,
          "sell_avg": 191.5,
          "net": -12
        }
      ]
    },
    {
      "date": "2026-06-23",
      "foreign_buy": 8030,
      "foreign_buy_avg": 193.47,
      "foreign_sell": 19155,
      "foreign_sell_avg": 191.44,
      "foreign_net": -11125,
      "top_foreign": [
        {
          "name": "摩根大通",
          "buy": 1449,
          "buy_avg": 191.59,
          "sell": 1163,
          "sell_avg": 190.09,
          "net": 286
        },
        {
          "name": "港商麥格理",
          "buy": 257,
          "buy_avg": 194.79,
          "sell": 148,
          "sell_avg": 189.79,
          "net": 109
        },
        {
          "name": "群益高盛",
          "buy": 18,
          "buy_avg": 191.18,
          "sell": 15,
          "sell_avg": 191.97,
          "net": 3
        }
      ],
      "top_foreign_sellers": [
        {
          "name": "星洲瑞銀",
          "buy": 940,
          "buy_avg": 193.34,
          "sell": 6034,
          "sell_avg": 192.72,
          "net": -5094
        },
        {
          "name": "摩根士丹利",
          "buy": 1994,
          "buy_avg": 194.2,
          "sell": 6528,
          "sell_avg": 190.75,
          "net": -4534
        },
        {
          "name": "花旗環球",
          "buy": 369,
          "buy_avg": 195.7,
          "sell": 1828,
          "sell_avg": 189.9,
          "net": -1459
        },
        {
          "name": "港商野村",
          "buy": 78,
          "buy_avg": 196.46,
          "sell": 283,
          "sell_avg": 187.74,
          "net": -205
        },
        {
          "name": "美林證券",
          "buy": 743,
          "buy_avg": 196.73,
          "sell": 895,
          "sell_avg": 192.29,
          "net": -152
        },
        {
          "name": "美商高盛亞",
          "buy": 2162,
          "buy_avg": 192.37,
          "sell": 2230,
          "sell_avg": 192.19,
          "net": -68
        },
        {
          "name": "上海匯豐",
          "buy": 20,
          "buy_avg": 192.97,
          "sell": 30,
          "sell_avg": 189,
          "net": -10
        }
      ]
    },
    {
      "date": "2026-06-24",
      "foreign_buy": 22700,
      "foreign_buy_avg": 194.8,
      "foreign_sell": 16808,
      "foreign_sell_avg": 194.2,
      "foreign_net": 5891,
      "top_foreign": [
        {
          "name": "星洲瑞銀",
          "buy": 6744,
          "buy_avg": 196.66,
          "sell": 2328,
          "sell_avg": 195.91,
          "net": 4416
        },
        {
          "name": "摩根士丹利",
          "buy": 5617,
          "buy_avg": 194.37,
          "sell": 3069,
          "sell_avg": 193.82,
          "net": 2548
        },
        {
          "name": "美商高盛亞",
          "buy": 6082,
          "buy_avg": 193.68,
          "sell": 5648,
          "sell_avg": 192.82,
          "net": 434
        },
        {
          "name": "港商麥格理",
          "buy": 342,
          "buy_avg": 194.74,
          "sell": 41,
          "sell_avg": 200,
          "net": 301
        },
        {
          "name": "上海匯豐",
          "buy": 51,
          "buy_avg": 193.83,
          "sell": 0,
          "sell_avg": 0,
          "net": 51
        },
        {
          "name": "港商野村",
          "buy": 171,
          "buy_avg": 191.97,
          "sell": 167,
          "sell_avg": 189.05,
          "net": 4
        }
      ],
      "top_foreign_sellers": [
        {
          "name": "摩根大通",
          "buy": 2111,
          "buy_avg": 193.51,
          "sell": 2955,
          "sell_avg": 195.48,
          "net": -844
        },
        {
          "name": "美林證券",
          "buy": 1141,
          "buy_avg": 194.68,
          "sell": 1911,
          "sell_avg": 195.31,
          "net": -770
        },
        {
          "name": "花旗環球",
          "buy": 429,
          "buy_avg": 195.06,
          "sell": 669,
          "sell_avg": 193.82,
          "net": -240
        },
        {
          "name": "群益高盛",
          "buy": 11,
          "buy_avg": 191.67,
          "sell": 20,
          "sell_avg": 194.89,
          "net": -9
        }
      ]
    },
    {
      "date": "2026-06-25",
      "foreign_buy": 6565,
      "foreign_buy_avg": 207.13,
      "foreign_sell": 16355,
      "foreign_sell_avg": 207.04,
      "foreign_net": -9790,
      "top_foreign": [
        {
          "name": "上海匯豐",
          "buy": 40,
          "buy_avg": 214.06,
          "sell": 5,
          "sell_avg": 220,
          "net": 35
        }
      ],
      "top_foreign_sellers": [
        {
          "name": "美商高盛亞",
          "buy": 1473,
          "buy_avg": 208.4,
          "sell": 4331,
          "sell_avg": 208.78,
          "net": -2858
        },
        {
          "name": "摩根大通",
          "buy": 1326,
          "buy_avg": 206.95,
          "sell": 3559,
          "sell_avg": 208.04,
          "net": -2233
        },
        {
          "name": "星洲瑞銀",
          "buy": 1686,
          "buy_avg": 203.21,
          "sell": 3236,
          "sell_avg": 203.18,
          "net": -1550
        },
        {
          "name": "美林證券",
          "buy": 496,
          "buy_avg": 209.49,
          "sell": 1849,
          "sell_avg": 209.68,
          "net": -1353
        },
        {
          "name": "摩根士丹利",
          "buy": 1349,
          "buy_avg": 209.66,
          "sell": 2522,
          "sell_avg": 204.43,
          "net": -1173
        },
        {
          "name": "港商野村",
          "buy": 119,
          "buy_avg": 204.63,
          "sell": 510,
          "sell_avg": 206.88,
          "net": -391
        },
        {
          "name": "港商麥格理",
          "buy": 0,
          "buy_avg": 0,
          "sell": 148,
          "sell_avg": 217.14,
          "net": -148
        },
        {
          "name": "花旗環球",
          "buy": 55,
          "buy_avg": 214.72,
          "sell": 163,
          "sell_avg": 216.17,
          "net": -108
        },
        {
          "name": "群益高盛",
          "buy": 21,
          "buy_avg": 207.64,
          "sell": 32,
          "sell_avg": 212.08,
          "net": -11
        }
      ]
    },
    {
      "date": "2026-06-26",
      "foreign_buy": 9524,
      "foreign_buy_avg": 205.15,
      "foreign_sell": 14738,
      "foreign_sell_avg": 206.96,
      "foreign_net": -5214,
      "top_foreign": [
        {
          "name": "星洲瑞銀",
          "buy": 2151,
          "buy_avg": 204.48,
          "sell": 1598,
          "sell_avg": 205.71,
          "net": 553
        },
        {
          "name": "港商麥格理",
          "buy": 263,
          "buy_avg": 206.6,
          "sell": 30,
          "sell_avg": 206,
          "net": 233
        },
        {
          "name": "花旗環球",
          "buy": 364,
          "buy_avg": 212.54,
          "sell": 152,
          "sell_avg": 206.41,
          "net": 212
        },
        {
          "name": "上海匯豐",
          "buy": 102,
          "buy_avg": 205.01,
          "sell": 39,
          "sell_avg": 205.06,
          "net": 63
        },
        {
          "name": "群益高盛",
          "buy": 44,
          "buy_avg": 207.54,
          "sell": 10,
          "sell_avg": 206.5,
          "net": 34
        }
      ],
      "top_foreign_sellers": [
        {
          "name": "美商高盛亞",
          "buy": 1259,
          "buy_avg": 205.92,
          "sell": 4269,
          "sell_avg": 206.66,
          "net": -3010
        },
        {
          "name": "摩根大通",
          "buy": 974,
          "buy_avg": 206.56,
          "sell": 3678,
          "sell_avg": 208.07,
          "net": -2704
        },
        {
          "name": "美林證券",
          "buy": 641,
          "buy_avg": 204.85,
          "sell": 998,
          "sell_avg": 206.8,
          "net": -357
        },
        {
          "name": "摩根士丹利",
          "buy": 3044,
          "buy_avg": 203.32,
          "sell": 3182,
          "sell_avg": 206.3,
          "net": -138
        },
        {
          "name": "港商野村",
          "buy": 682,
          "buy_avg": 207.64,
          "sell": 782,
          "sell_avg": 209.07,
          "net": -100
        }
      ]
    },
    {
      "date": "2026-06-29",
      "foreign_buy": 4402,
      "foreign_buy_avg": 207.95,
      "foreign_sell": 10180,
      "foreign_sell_avg": 208.25,
      "foreign_net": -5778,
      "top_foreign": [
        {
          "name": "美林證券",
          "buy": 1379,
          "buy_avg": 207.63,
          "sell": 842,
          "sell_avg": 208.52,
          "net": 537
        },
        {
          "name": "摩根士丹利",
          "buy": 1724,
          "buy_avg": 208.08,
          "sell": 1254,
          "sell_avg": 208.1,
          "net": 470
        },
        {
          "name": "港商麥格理",
          "buy": 38,
          "buy_avg": 208.5,
          "sell": 0,
          "sell_avg": 0,
          "net": 38
        },
        {
          "name": "群益高盛",
          "buy": 23,
          "buy_avg": 207.46,
          "sell": 13,
          "sell_avg": 209.14,
          "net": 10
        },
        {
          "name": "上海匯豐",
          "buy": 50,
          "buy_avg": 207.59,
          "sell": 44,
          "sell_avg": 208.5,
          "net": 6
        }
      ],
      "top_foreign_sellers": [
        {
          "name": "美商高盛亞",
          "buy": 324,
          "buy_avg": 208.91,
          "sell": 2935,
          "sell_avg": 208.23,
          "net": -2611
        },
        {
          "name": "摩根大通",
          "buy": 189,
          "buy_avg": 207.38,
          "sell": 2012,
          "sell_avg": 208.17,
          "net": -1823
        },
        {
          "name": "星洲瑞銀",
          "buy": 240,
          "buy_avg": 208.5,
          "sell": 1889,
          "sell_avg": 207.59,
          "net": -1649
        },
        {
          "name": "港商野村",
          "buy": 199,
          "buy_avg": 208.62,
          "sell": 623,
          "sell_avg": 208.54,
          "net": -424
        },
        {
          "name": "花旗環球",
          "buy": 236,
          "buy_avg": 206.98,
          "sell": 568,
          "sell_avg": 210.42,
          "net": -332
        }
      ]
    }
  ]
}